CHANGES.txt
CONTRIBUTORS.txt
MANIFEST.in
README.txt
setup.py
docs/LICENSE.GPL
docs/LICENSE.txt
src/ecreall/__init__.py
src/ecreall.helpers.testing.egg-info/PKG-INFO
src/ecreall.helpers.testing.egg-info/SOURCES.txt
src/ecreall.helpers.testing.egg-info/dependency_links.txt
src/ecreall.helpers.testing.egg-info/entry_points.txt
src/ecreall.helpers.testing.egg-info/namespace_packages.txt
src/ecreall.helpers.testing.egg-info/not-zip-safe
src/ecreall.helpers.testing.egg-info/requires.txt
src/ecreall.helpers.testing.egg-info/top_level.txt
src/ecreall/helpers/__init__.py
src/ecreall/helpers/testing/__init__.py
src/ecreall/helpers/testing/base.py
src/ecreall/helpers/testing/configure.zcml
src/ecreall/helpers/testing/contentrules.py
src/ecreall/helpers/testing/member.py
src/ecreall/helpers/testing/profile.py
src/ecreall/helpers/testing/search.py
src/ecreall/helpers/testing/workflow.py