Metadata-Version: 1.1
Name: ecreall.helpers.testing
Version: 1.4
Summary: Helpers for testing often used at Ecreall
Home-page: http://svn.plone.org/svn/collective/
Author: UNKNOWN
Author-email: UNKNOWN
License: gpl
Platform: UNKNOWN
Classifier: Programming Language :: Python
